dist/ka_apg-2022.3.0.tar.gz
ka_apg/__init__.py
ka_apg/__version__.py
ka_apg/asyhttp.py
ka_apg/email.py
ka_apg/hf.py
ka_apg/http.py
ka_apg/mgo.py
ka_apg/nlp.py
ka_apg/path.py
ka_apg/paths.py
ka_apg/xlsx.py
ka_apg/data/__init__.py
ka_apg/data/log.yml
ka_apg/data/pgu.yml
ka_apg-2022.3.0.dist-info/LICENSE.txt
ka_apg-2022.3.0.dist-info/METADATA
ka_apg-2022.3.0.dist-info/WHEEL
ka_apg-2022.3.0.dist-info/top_level.txt
ka_apg-2022.3.0.dist-info/RECORD
