Metadata-Version: 2.1
Name: ka-apg
Version: 2022.3.0
Summary: Special Utilities
Author-email: Bernd Stroehle <bernd.stroehle@bs29.com>
Maintainer-email: Bernd Stroehle <bernd.stroehle@bs29.com>
License: #
Project-URL: Source Code, https://github.com/bs29/ka_apg/tree/master
Project-URL: Homepage, https://kosakya.de/
Project-URL: Documentation, https://ka-apc.readthedocs.io/en/latest
Project-URL: Apache-2.0 License, https://apache.org/licenses/LICENSE-2.0
Requires-Python: >=3.10
License-File: LICENSE.txt
Requires-Dist: aiohttp (>=3.8.3)
Requires-Dist: email-validator (>=1.3.0)
Requires-Dist: humanfriendly (>=10.0)
Requires-Dist: ka-utg (>=2022.3.0)
Requires-Dist: ka-uts (>=2022.3.0)
Requires-Dist: openpyxl (>=3.0.10)
Requires-Dist: pyexcel (>=0.7.0)
Requires-Dist: pymongo (>=4.3.3)
Requires-Dist: requests (>=2.28.2)
Requires-Dist: spacy (>=3.5.0)
Requires-Dist: urllib3 (>=1.26.14)
Requires-Dist: xlrd (>=2.0.1)
Requires-Dist: xmltodict (>=0.13.0)
